powerhub/__init__.py
powerhub/__main__.py
powerhub/app.py
powerhub/args.py
powerhub/dhkex.py
powerhub/directories.py
powerhub/flask.py
powerhub/hiddenapp.py
powerhub/logging.py
powerhub/modules.py
powerhub/parameters.py
powerhub/payloads.py
powerhub/po_args.py
powerhub/repos.py
powerhub/reverseproxy.py
powerhub/sql.py
powerhub/stager.py
powerhub/tools.py
powerhub/upload.py
powerhub/variables.txt
powerhub/webdav.py
powerhub/decoy/Generic.psm1
powerhub/decoy/LICENSE
powerhub/decoy/M365DSCAgent.psm1
powerhub/decoy/M365DSCCheckProperties.psm1
powerhub/decoy/M365DSCDocGenerator.psm1
powerhub/decoy/M365DSCEmojis.psm1
powerhub/decoy/M365DSCErrorHandler.psm1
powerhub/decoy/M365DSCExoResourceUtils.psm1
powerhub/decoy/M365DSCLogEngine.psm1
powerhub/decoy/M365DSCPermissions.psm1
powerhub/decoy/M365DSCReport.psm1
powerhub/decoy/M365DSCResourceGenerator.psm1
powerhub/decoy/M365DSCReverse.psm1
powerhub/decoy/M365DSCStringEncoding.psm1
powerhub/decoy/M365DSCStubsUtility.psm1
powerhub/decoy/M365DSCTelemetryEngine.psm1
powerhub/decoy/M365DSCUtil.psm1
powerhub/decoy/MSFT_AADAdministrativeUnit.psm1
powerhub/decoy/MSFT_AADApplication.psm1
powerhub/decoy/MSFT_AADAuthorizationPolicy.psm1
powerhub/decoy/MSFT_AADConditionalAccessPolicy.psm1
powerhub/decoy/MSFT_AADEntitlementManagementAccessPackage.psm1
powerhub/decoy/MSFT_AADEntitlementManagementAccessPackageCatalog.psm1
powerhub/decoy/MSFT_AADEntitlementManagementAccessPackageCatalogResource.psm1
powerhub/decoy/MSFT_AADGroup.psm1
powerhub/decoy/MSFT_AADGroupLifecyclePolicy.psm1
powerhub/decoy/MSFT_AADGroupsNamingPolicy.psm1
powerhub/decoy/MSFT_AADGroupsSettings.psm1
powerhub/decoy/MSFT_AADNamedLocationPolicy.psm1
powerhub/decoy/MSFT_AADRoleDefinition.psm1
powerhub/decoy/MSFT_AADRoleSetting.psm1
powerhub/decoy/MSFT_AADSecurityDefaults.psm1
powerhub/decoy/MSFT_AADServicePrincipal.psm1
powerhub/decoy/MSFT_AADTenantDetails.psm1
powerhub/decoy/MSFT_AADTokenLifetimePolicy.psm1
powerhub/decoy/MSFT_AADUser.psm1
powerhub-2.0.10.dist-info/METADATA
powerhub-2.0.10.dist-info/WHEEL
powerhub-2.0.10.dist-info/entry_points.txt
powerhub-2.0.10.dist-info/top_level.txt
powerhub-2.0.10.dist-info/RECORD
