Metadata-Version: 2.1
Name: powerhub
Version: 2.0.10
Summary: A post exploitation tool based on a web application, focusing on bypassing endpoint protection and application whitelisting
Author-email: Adrian Vollmer <computerfluesterer@protonmail.com>
License: MIT License
Project-URL: Homepage, https://github.com/AdrianVollmer/PowerHub
Project-URL: Bug Tracker, https://github.com/AdrianVollmer/PowerHub/issues
Keywords: pentest,c2,powershell,obfuscation,post-exploitation
Classifier: Operating System :: POSIX :: Linux
Classifier: Programming Language :: Python
Classifier: Programming Language :: Python :: 3
Classifier: Programming Language :: Python :: 3.7
Classifier: Programming Language :: Python :: 3.8
Classifier: Programming Language :: Python :: 3.9
Classifier: Programming Language :: Python :: 3.10
Requires-Python: >=3.7
Requires-Dist: cheroot
Requires-Dist: cryptography>=42
Requires-Dist: dnspython>=2.3
Requires-Dist: Flask>=1.0.2
Requires-Dist: Flask-SocketIO>=5.3.0
Requires-Dist: flask-sqlalchemy>=3.0
Requires-Dist: importlib-metadata; python_version < "3.8"
Requires-Dist: Jinja2>=3.0
Requires-Dist: pyOpenSSL
Requires-Dist: python-magic
Requires-Dist: requests
Requires-Dist: service_identity
Requires-Dist: simple-websocket
Requires-Dist: sqlalchemy>=2.0
Requires-Dist: python-socketio>=5.8
Requires-Dist: twisted>=18.9.0
Requires-Dist: watchdog
Requires-Dist: werkzeug>=0.15
Requires-Dist: wsgidav>=3.0.0
Provides-Extra: tests
Requires-Dist: pytest; extra == "tests"
Requires-Dist: flake8; extra == "tests"
Requires-Dist: beautifulsoup4; extra == "tests"
Requires-Dist: lxml; extra == "tests"
Provides-Extra: dev
Requires-Dist: tox; extra == "dev"
